{
  "type": "pfm:furniture",
  "ingredients": [
    {
      "item": "minecraft:green_wool"
    },
    {
      "item": "minecraft:green_wool"
    },
    {
      "item": "minecraft:green_wool"
    },
    {
      "item": "tconstruct:stripped_greenheart_log"
    },
    {
      "item": "tconstruct:stripped_greenheart_log"
    }
  ],
  "result": {
    "item": "pfm:basic_lamp",
    "tag": {
      "BlockEntityTag": {
        "color": "green",
        "variant": "tconstruct:greenheart"
      }
    }
  }
}